[
	{
		"name": "томатный суп",
		"date": "2025-04-23"
	},
	{
		"name": "венские сосиски",
		"date": "2025-03-14"
	},
	{
		"name": "суп харчо",
		"date": "2025-02-28"
	},
	{
		"name": "суп грибной",
		"date": "2025-03-05"
	},
	{
		"name": "суп солянка",
		"date": "2025-03-07"
	},
	{
		"name": "куриная грудинка (копчёная)",
		"date": "2025-03-28"
	},
	{
		"name": "свиная грудинка (отрезок)",
		"date": "2025-03-21"
	},
	{
		"name": "бекон",
		"date": "2025-04-17"
	},
	{
		"name": "квашеная капуста",
		"date": "2025-03-15"
	},
	{
		"name": "форель слабосолёная",
		"date": "2025-04-13"
	},
	{
		"name": "паштет гусиный",
		"date": "2025-03-16"
	},
	{
		"name": "салат чука",
		"date": "2025-05-03"
	},
	{
		"name": "творог",
		"date": "2025-03-13"
	}
]